sec.py
sec-0.3.0.dist-info/LICENSE
sec-0.3.0.dist-info/WHEEL
sec-0.3.0.dist-info/METADATA
sec-0.3.0.dist-info/RECORD
