Metadata-Version: 2.1
Name: sec
Version: 0.3.0
Summary: Tiny Python library for secrets
License: MIT
Author: Paris Kasidiaris
Author-email: paris@sourcelair.com
Requires-Python: >=3.6,<4.0
Classifier: License :: OSI Approved :: MIT License
Classifier: Programming Language :: Python :: 3
Classifier: Programming Language :: Python :: 3.6
Classifier: Programming Language :: Python :: 3.7
Classifier: Programming Language :: Python :: 3.8
Classifier: Programming Language :: Python :: 3.9
